[
  {
    "tenantId": "{{rdmTenant}}",
    "type": "rdm/lookupTypes/StockExchanges",
    "code": "KOME",
    "enabled": true,
    "startDate": "0",
    "endDate": "0",
    "updatedBy": "proactive_monitoring_service",
    "version": "1",
    "sourceMappings": [
      {
        "source": "Reltio",
        "values": [
          {
            "code": "KOME",
            "value": "KOMERCNI BANKA, A.S.",
            "canonicalValue": "true",
            "downStreamDefaultValue": true,
            "enabled": true
          }
        ]
      }
    ]
  },
  {
    "tenantId": "{{rdmTenant}}",
    "type": "rdm/lookupTypes/StockExchanges",
    "code": "KOTF",
    "enabled": true,
    "startDate": "0",
    "endDate": "0",
    "updatedBy": "proactive_monitoring_service",
    "version": "1",
    "sourceMappings": [
      {
        "source": "Reltio",
        "values": [
          {
            "code": "KOTF",
            "value": "OTFLINK",
            "canonicalValue": "true",
            "downStreamDefaultValue": true,
            "enabled": true
          }
        ]
      }
    ]
  },
  {
    "tenantId": "{{rdmTenant}}",
    "type": "rdm/lookupTypes/StockExchanges",
    "code": "KRME",
    "enabled": true,
    "startDate": "0",
    "endDate": "0",
    "updatedBy": "proactive_monitoring_service",
    "version": "1",
    "sourceMappings": [
      {
        "source": "Reltio",
        "values": [
          {
            "code": "KRME",
            "value": "PAYWARD MENA HOLDINGS LTD.",
            "canonicalValue": "true",
            "downStreamDefaultValue": true,
            "enabled": true
          }
        ]
      }
    ]
  },
  {
    "tenantId": "{{rdmTenant}}",
    "type": "rdm/lookupTypes/StockExchanges",
    "code": "LAFD",
    "enabled": true,
    "startDate": "0",
    "endDate": "0",
    "updatedBy": "proactive_monitoring_service",
    "version": "1",
    "sourceMappings": [
      {
        "source": "Reltio",
        "values": [
          {
            "code": "LAFD",
            "value": "FLOW DARK",
            "canonicalValue": "true",
            "downStreamDefaultValue": true,
            "enabled": true
          }
        ]
      }
    ]
  },
  {
    "tenantId": "{{rdmTenant}}",
    "type": "rdm/lookupTypes/StockExchanges",
    "code": "LAFL",
    "enabled": true,
    "startDate": "0",
    "endDate": "0",
    "updatedBy": "proactive_monitoring_service",
    "version": "1",
    "sourceMappings": [
      {
        "source": "Reltio",
        "values": [
          {
            "code": "LAFL",
            "value": "LAVAFLOW ECN",
            "canonicalValue": "true",
            "downStreamDefaultValue": true,
            "enabled": true
          }
        ]
      }
    ]
  },
  {
    "tenantId": "{{rdmTenant}}",
    "type": "rdm/lookupTypes/StockExchanges",
    "code": "LAFX",
    "enabled": true,
    "startDate": "0",
    "endDate": "0",
    "updatedBy": "proactive_monitoring_service",
    "version": "1",
    "sourceMappings": [
      {
        "source": "Reltio",
        "values": [
          {
            "code": "LAFX",
            "value": "LAVAFX",
            "canonicalValue": "true",
            "downStreamDefaultValue": true,
            "enabled": true
          }
        ]
      }
    ]
  },
  {
    "tenantId": "{{rdmTenant}}",
    "type": "rdm/lookupTypes/StockExchanges",
    "code": "LAMP",
    "enabled": true,
    "startDate": "0",
    "endDate": "0",
    "updatedBy": "proactive_monitoring_service",
    "version": "1",
    "sourceMappings": [
      {
        "source": "Reltio",
        "values": [
          {
            "code": "LAMP",
            "value": "LAMPOST CAPITAL",
            "canonicalValue": "true",
            "downStreamDefaultValue": true,
            "enabled": true
          }
        ]
      }
    ]
  },
  {
    "tenantId": "{{rdmTenant}}",
    "type": "rdm/lookupTypes/StockExchanges",
    "code": "LASF",
    "enabled": true,
    "startDate": "0",
    "endDate": "0",
    "updatedBy": "proactive_monitoring_service",
    "version": "1",
    "sourceMappings": [
      {
        "source": "Reltio",
        "values": [
          {
            "code": "LASF",
            "value": "LATAM SEF",
            "canonicalValue": "true",
            "downStreamDefaultValue": true,
            "enabled": true
          }
        ]
      }
    ]
  },
  {
    "tenantId": "{{rdmTenant}}",
    "type": "rdm/lookupTypes/StockExchanges",
    "code": "LASP",
    "enabled": true,
    "startDate": "0",
    "endDate": "0",
    "updatedBy": "proactive_monitoring_service",
    "version": "1",
    "sourceMappings": [
      {
        "source": "Reltio",
        "values": [
          {
            "code": "LASP",
            "value": "LAN AND SPAR BANK A/S",
            "canonicalValue": "true",
            "downStreamDefaultValue": true,
            "enabled": true
          }
        ]
      }
    ]
  },
  {
    "tenantId": "{{rdmTenant}}",
    "type": "rdm/lookupTypes/StockExchanges",
    "code": "LATG",
    "enabled": true,
    "startDate": "0",
    "endDate": "0",
    "updatedBy": "proactive_monitoring_service",
    "version": "1",
    "sourceMappings": [
      {
        "source": "Reltio",
        "values": [
          {
            "code": "LATG",
            "value": "GFI SECURITIES LLC - CREDITMATCH (LATG)",
            "canonicalValue": "true",
            "downStreamDefaultValue": true,
            "enabled": true
          }
        ]
      }
    ]
  },
  {
    "tenantId": "{{rdmTenant}}",
    "type": "rdm/lookupTypes/StockExchanges",
    "code": "LAVA",
    "enabled": true,
    "startDate": "0",
    "endDate": "0",
    "updatedBy": "proactive_monitoring_service",
    "version": "1",
    "sourceMappings": [
      {
        "source": "Reltio",
        "values": [
          {
            "code": "LAVA",
            "value": "LAVA TRADING (CITI)",
            "canonicalValue": "true",
            "downStreamDefaultValue": true,
            "enabled": true
          }
        ]
      }
    ]
  },
  {
    "tenantId": "{{rdmTenant}}",
    "type": "rdm/lookupTypes/StockExchanges",
    "code": "LBBW",
    "enabled": true,
    "startDate": "0",
    "endDate": "0",
    "updatedBy": "proactive_monitoring_service",
    "version": "1",
    "sourceMappings": [
      {
        "source": "Reltio",
        "values": [
          {
            "code": "LBBW",
            "value": "LBBW - LANDESBANK BADEN-WUERTTEMBERG",
            "canonicalValue": "true",
            "downStreamDefaultValue": true,
            "enabled": true
          }
        ]
      }
    ]
  },
  {
    "tenantId": "{{rdmTenant}}",
    "type": "rdm/lookupTypes/StockExchanges",
    "code": "LBCM",
    "enabled": true,
    "startDate": "0",
    "endDate": "0",
    "updatedBy": "proactive_monitoring_service",
    "version": "1",
    "sourceMappings": [
      {
        "source": "Reltio",
        "values": [
          {
            "code": "LBCM",
            "value": "LLOYDS BANK CORPORATE MARKETS",
            "canonicalValue": "true",
            "downStreamDefaultValue": true,
            "enabled": true
          }
        ]
      }
    ]
  },
  {
    "tenantId": "{{rdmTenant}}",
    "type": "rdm/lookupTypes/StockExchanges",
    "code": "LBCW",
    "enabled": true,
    "startDate": "0",
    "endDate": "0",
    "updatedBy": "proactive_monitoring_service",
    "version": "1",
    "sourceMappings": [
      {
        "source": "Reltio",
        "values": [
          {
            "code": "LBCW",
            "value": "LLOYDS BANK CORPORATE MARKETS WERTPAPIERHANDELSBANK GMBH",
            "canonicalValue": "true",
            "downStreamDefaultValue": true,
            "enabled": true
          }
        ]
      }
    ]
  },
  {
    "tenantId": "{{rdmTenant}}",
    "type": "rdm/lookupTypes/StockExchanges",
    "code": "LBUL",
    "enabled": true,
    "startDate": "0",
    "endDate": "0",
    "updatedBy": "proactive_monitoring_service",
    "version": "1",
    "sourceMappings": [
      {
        "source": "Reltio",
        "values": [
          {
            "code": "LBUL",
            "value": "BULGARIAN STOCK EXCHANGE - SBL",
            "canonicalValue": "true",
            "downStreamDefaultValue": true,
            "enabled": true
          }
        ]
      }
    ]
  },
  {
    "tenantId": "{{rdmTenant}}",
    "type": "rdm/lookupTypes/StockExchanges",
    "code": "LBWL",
    "enabled": true,
    "startDate": "0",
    "endDate": "0",
    "updatedBy": "proactive_monitoring_service",
    "version": "1",
    "sourceMappings": [
      {
        "source": "Reltio",
        "values": [
          {
            "code": "LBWL",
            "value": "LBBW - LANDESBANK BADEN-WUERTTEMBERG - LIQUIDITY PROVIDER",
            "canonicalValue": "true",
            "downStreamDefaultValue": true,
            "enabled": true
          }
        ]
      }
    ]
  },
  {
    "tenantId": "{{rdmTenant}}",
    "type": "rdm/lookupTypes/StockExchanges",
    "code": "LBWS",
    "enabled": true,
    "startDate": "0",
    "endDate": "0",
    "updatedBy": "proactive_monitoring_service",
    "version": "1",
    "sourceMappings": [
      {
        "source": "Reltio",
        "values": [
          {
            "code": "LBWS",
            "value": "LBBW - LANDESBANK BADEN-WUERTTEMBERG - SYSTEMATIC INTERNALISER",
            "canonicalValue": "true",
            "downStreamDefaultValue": true,
            "enabled": true
          }
        ]
      }
    ]
  },
  {
    "tenantId": "{{rdmTenant}}",
    "type": "rdm/lookupTypes/StockExchanges",
    "code": "LCHC",
    "enabled": true,
    "startDate": "0",
    "endDate": "0",
    "updatedBy": "proactive_monitoring_service",
    "version": "1",
    "sourceMappings": [
      {
        "source": "Reltio",
        "values": [
          {
            "code": "LCHC",
            "value": "LCH.CLEARNET",
            "canonicalValue": "true",
            "downStreamDefaultValue": true,
            "enabled": true
          }
        ]
      }
    ]
  },
  {
    "tenantId": "{{rdmTenant}}",
    "type": "rdm/lookupTypes/StockExchanges",
    "code": "LCUR",
    "enabled": true,
    "startDate": "0",
    "endDate": "0",
    "updatedBy": "proactive_monitoring_service",
    "version": "1",
    "sourceMappings": [
      {
        "source": "Reltio",
        "values": [
          {
            "code": "LCUR",
            "value": "CURRENEX LDFX",
            "canonicalValue": "true",
            "downStreamDefaultValue": true,
            "enabled": true
          }
        ]
      }
    ]
  },
  {
    "tenantId": "{{rdmTenant}}",
    "type": "rdm/lookupTypes/StockExchanges",
    "code": "LEBV",
    "enabled": true,
    "startDate": "0",
    "endDate": "0",
    "updatedBy": "proactive_monitoring_service",
    "version": "1",
    "sourceMappings": [
      {
        "source": "Reltio",
        "values": [
          {
            "code": "LEBV",
            "value": "LEDGEREDGE B.V.",
            "canonicalValue": "true",
            "downStreamDefaultValue": true,
            "enabled": true
          }
        ]
      }
    ]
  },
  {
    "tenantId": "{{rdmTenant}}",
    "type": "rdm/lookupTypes/StockExchanges",
    "code": "LEDG",
    "enabled": true,
    "startDate": "0",
    "endDate": "0",
    "updatedBy": "proactive_monitoring_service",
    "version": "1",
    "sourceMappings": [
      {
        "source": "Reltio",
        "values": [
          {
            "code": "LEDG",
            "value": "LEDGERX",
            "canonicalValue": "true",
            "downStreamDefaultValue": true,
            "enabled": true
          }
        ]
      }
    ]
  },
  {
    "tenantId": "{{rdmTenant}}",
    "type": "rdm/lookupTypes/StockExchanges",
    "code": "LELE",
    "enabled": true,
    "startDate": "0",
    "endDate": "0",
    "updatedBy": "proactive_monitoring_service",
    "version": "1",
    "sourceMappings": [
      {
        "source": "Reltio",
        "values": [
          {
            "code": "LELE",
            "value": "LEDGEREDGE",
            "canonicalValue": "true",
            "downStreamDefaultValue": true,
            "enabled": true
          }
        ]
      }
    ]
  },
  {
    "tenantId": "{{rdmTenant}}",
    "type": "rdm/lookupTypes/StockExchanges",
    "code": "LESI",
    "enabled": true,
    "startDate": "0",
    "endDate": "0",
    "updatedBy": "proactive_monitoring_service",
    "version": "1",
    "sourceMappings": [
      {
        "source": "Reltio",
        "values": [
          {
            "code": "LESI",
            "value": "LEDGEREDGE SECURITIES INC.",
            "canonicalValue": "true",
            "downStreamDefaultValue": true,
            "enabled": true
          }
        ]
      }
    ]
  },
  {
    "tenantId": "{{rdmTenant}}",
    "type": "rdm/lookupTypes/StockExchanges",
    "code": "LEUE",
    "enabled": true,
    "startDate": "0",
    "endDate": "0",
    "updatedBy": "proactive_monitoring_service",
    "version": "1",
    "sourceMappings": [
      {
        "source": "Reltio",
        "values": [
          {
            "code": "LEUE",
            "value": "LIQUIDNET EU LIMITED EQUITY MTF",
            "canonicalValue": "true",
            "downStreamDefaultValue": true,
            "enabled": true
          }
        ]
      }
    ]
  },
  {
    "tenantId": "{{rdmTenant}}",
    "type": "rdm/lookupTypes/StockExchanges",
    "code": "LEUF",
    "enabled": true,
    "startDate": "0",
    "endDate": "0",
    "updatedBy": "proactive_monitoring_service",
    "version": "1",
    "sourceMappings": [
      {
        "source": "Reltio",
        "values": [
          {
            "code": "LEUF",
            "value": "LIQUIDNET EU LIMITED FIXED INCOME MTF",
            "canonicalValue": "true",
            "downStreamDefaultValue": true,
            "enabled": true
          }
        ]
      }
    ]
  },
  {
    "tenantId": "{{rdmTenant}}",
    "type": "rdm/lookupTypes/StockExchanges",
    "code": "LEVL",
    "enabled": true,
    "startDate": "0",
    "endDate": "0",
    "updatedBy": "proactive_monitoring_service",
    "version": "1",
    "sourceMappings": [
      {
        "source": "Reltio",
        "values": [
          {
            "code": "LEVL",
            "value": "LEVEL ATS",
            "canonicalValue": "true",
            "downStreamDefaultValue": true,
            "enabled": true
          }
        ]
      }
    ]
  },
  {
    "tenantId": "{{rdmTenant}}",
    "type": "rdm/lookupTypes/StockExchanges",
    "code": "LICA",
    "enabled": true,
    "startDate": "0",
    "endDate": "0",
    "updatedBy": "proactive_monitoring_service",
    "version": "1",
    "sourceMappings": [
      {
        "source": "Reltio",
        "values": [
          {
            "code": "LICA",
            "value": "LIQUIDNET CANADA ATS",
            "canonicalValue": "true",
            "downStreamDefaultValue": true,
            "enabled": true
          }
        ]
      }
    ]
  },
  {
    "tenantId": "{{rdmTenant}}",
    "type": "rdm/lookupTypes/StockExchanges",
    "code": "LIFI",
    "enabled": true,
    "startDate": "0",
    "endDate": "0",
    "updatedBy": "proactive_monitoring_service",
    "version": "1",
    "sourceMappings": [
      {
        "source": "Reltio",
        "values": [
          {
            "code": "LIFI",
            "value": "LIQUIDNET, INC. FIXED INCOME ATS",
            "canonicalValue": "true",
            "downStreamDefaultValue": true,
            "enabled": true
          }
        ]
      }
    ]
  },
  {
    "tenantId": "{{rdmTenant}}",
    "type": "rdm/lookupTypes/StockExchanges",
    "code": "LIGA",
    "enabled": true,
    "startDate": "0",
    "endDate": "0",
    "updatedBy": "proactive_monitoring_service",
    "version": "1",
    "sourceMappings": [
      {
        "source": "Reltio",
        "values": [
          {
            "code": "LIGA",
            "value": "LIGA BANK EG",
            "canonicalValue": "true",
            "downStreamDefaultValue": true,
            "enabled": true
          }
        ]
      }
    ]
  },
  {
    "tenantId": "{{rdmTenant}}",
    "type": "rdm/lookupTypes/StockExchanges",
    "code": "LIQF",
    "enabled": true,
    "startDate": "0",
    "endDate": "0",
    "updatedBy": "proactive_monitoring_service",
    "version": "1",
    "sourceMappings": [
      {
        "source": "Reltio",
        "values": [
          {
            "code": "LIQF",
            "value": "LIQUIDNET EUROPE LIMITED",
            "canonicalValue": "true",
            "downStreamDefaultValue": true,
            "enabled": true
          }
        ]
      }
    ]
  },
  {
    "tenantId": "{{rdmTenant}}",
    "type": "rdm/lookupTypes/StockExchanges",
    "code": "LIQH",
    "enabled": true,
    "startDate": "0",
    "endDate": "0",
    "updatedBy": "proactive_monitoring_service",
    "version": "1",
    "sourceMappings": [
      {
        "source": "Reltio",
        "values": [
          {
            "code": "LIQH",
            "value": "LIQUIDNET H20",
            "canonicalValue": "true",
            "downStreamDefaultValue": true,
            "enabled": true
          }
        ]
      }
    ]
  },
  {
    "tenantId": "{{rdmTenant}}",
    "type": "rdm/lookupTypes/StockExchanges",
    "code": "LIQU",
    "enabled": true,
    "startDate": "0",
    "endDate": "0",
    "updatedBy": "proactive_monitoring_service",
    "version": "1",
    "sourceMappings": [
      {
        "source": "Reltio",
        "values": [
          {
            "code": "LIQU",
            "value": "LIQUIDNET SYSTEMS",
            "canonicalValue": "true",
            "downStreamDefaultValue": true,
            "enabled": true
          }
        ]
      }
    ]
  },
  {
    "tenantId": "{{rdmTenant}}",
    "type": "rdm/lookupTypes/StockExchanges",
    "code": "LISX",
    "enabled": true,
    "startDate": "0",
    "endDate": "0",
    "updatedBy": "proactive_monitoring_service",
    "version": "1",
    "sourceMappings": [
      {
        "source": "Reltio",
        "values": [
          {
            "code": "LISX",
            "value": "CBOE  EUROPE - LIS SERVICE",
            "canonicalValue": "true",
            "downStreamDefaultValue": true,
            "enabled": true
          }
        ]
      }
    ]
  },
  {
    "tenantId": "{{rdmTenant}}",
    "type": "rdm/lookupTypes/StockExchanges",
    "code": "LISZ",
    "enabled": true,
    "startDate": "0",
    "endDate": "0",
    "updatedBy": "proactive_monitoring_service",
    "version": "1",
    "sourceMappings": [
      {
        "source": "Reltio",
        "values": [
          {
            "code": "LISZ",
            "value": "CBOE EUROPE - LIS SERVICE (NL)",
            "canonicalValue": "true",
            "downStreamDefaultValue": true,
            "enabled": true
          }
        ]
      }
    ]
  },
  {
    "tenantId": "{{rdmTenant}}",
    "type": "rdm/lookupTypes/StockExchanges",
    "code": "LIUH",
    "enabled": true,
    "startDate": "0",
    "endDate": "0",
    "updatedBy": "proactive_monitoring_service",
    "version": "1",
    "sourceMappings": [
      {
        "source": "Reltio",
        "values": [
          {
            "code": "LIUH",
            "value": "LIQUIDNET, INC. H2O ATS",
            "canonicalValue": "true",
            "downStreamDefaultValue": true,
            "enabled": true
          }
        ]
      }
    ]
  },
  {
    "tenantId": "{{rdmTenant}}",
    "type": "rdm/lookupTypes/StockExchanges",
    "code": "LIUS",
    "enabled": true,
    "startDate": "0",
    "endDate": "0",
    "updatedBy": "proactive_monitoring_service",
    "version": "1",
    "sourceMappings": [
      {
        "source": "Reltio",
        "values": [
          {
            "code": "LIUS",
            "value": "LIQUIDNET, INC.",
            "canonicalValue": "true",
            "downStreamDefaultValue": true,
            "enabled": true
          }
        ]
      }
    ]
  },
  {
    "tenantId": "{{rdmTenant}}",
    "type": "rdm/lookupTypes/StockExchanges",
    "code": "LLAT",
    "enabled": true,
    "startDate": "0",
    "endDate": "0",
    "updatedBy": "proactive_monitoring_service",
    "version": "1",
    "sourceMappings": [
      {
        "source": "Reltio",
        "values": [
          {
            "code": "LLAT",
            "value": "LIECHTENSTEINISCHE LANDESBANK (OSTERREICH) AG",
            "canonicalValue": "true",
            "downStreamDefaultValue": true,
            "enabled": true
          }
        ]
      }
    ]
  },
  {
    "tenantId": "{{rdmTenant}}",
    "type": "rdm/lookupTypes/StockExchanges",
    "code": "LMAD",
    "enabled": true,
    "startDate": "0",
    "endDate": "0",
    "updatedBy": "proactive_monitoring_service",
    "version": "1",
    "sourceMappings": [
      {
        "source": "Reltio",
        "values": [
          {
            "code": "LMAD",
            "value": "LMAX - DERIVATIVES",
            "canonicalValue": "true",
            "downStreamDefaultValue": true,
            "enabled": true
          }
        ]
      }
    ]
  },
  {
    "tenantId": "{{rdmTenant}}",
    "type": "rdm/lookupTypes/StockExchanges",
    "code": "LMAE",
    "enabled": true,
    "startDate": "0",
    "endDate": "0",
    "updatedBy": "proactive_monitoring_service",
    "version": "1",
    "sourceMappings": [
      {
        "source": "Reltio",
        "values": [
          {
            "code": "LMAE",
            "value": "LMAX - EQUITIES",
            "canonicalValue": "true",
            "downStreamDefaultValue": true,
            "enabled": true
          }
        ]
      }
    ]
  },
  {
    "tenantId": "{{rdmTenant}}",
    "type": "rdm/lookupTypes/StockExchanges",
    "code": "LMAF",
    "enabled": true,
    "startDate": "0",
    "endDate": "0",
    "updatedBy": "proactive_monitoring_service",
    "version": "1",
    "sourceMappings": [
      {
        "source": "Reltio",
        "values": [
          {
            "code": "LMAF",
            "value": "LMAX - FX AND CASH-SETTLED DERIVATIVES",
            "canonicalValue": "true",
            "downStreamDefaultValue": true,
            "enabled": true
          }
        ]
      }
    ]
  },
  {
    "tenantId": "{{rdmTenant}}",
    "type": "rdm/lookupTypes/StockExchanges",
    "code": "LMAO",
    "enabled": true,
    "startDate": "0",
    "endDate": "0",
    "updatedBy": "proactive_monitoring_service",
    "version": "1",
    "sourceMappings": [
      {
        "source": "Reltio",
        "values": [
          {
            "code": "LMAO",
            "value": "LMAX - INDICES/RATES/COMMODITIES",
            "canonicalValue": "true",
            "downStreamDefaultValue": true,
            "enabled": true
          }
        ]
      }
    ]
  },
  {
    "tenantId": "{{rdmTenant}}",
    "type": "rdm/lookupTypes/StockExchanges",
    "code": "LMAS",
    "enabled": true,
    "startDate": "0",
    "endDate": "0",
    "updatedBy": "proactive_monitoring_service",
    "version": "1",
    "sourceMappings": [
      {
        "source": "Reltio",
        "values": [
          {
            "code": "LMAS",
            "value": "LMAX EXCHANGE SINGAPORE - NDFS",
            "canonicalValue": "true",
            "downStreamDefaultValue": true,
            "enabled": true
          }
        ]
      }
    ]
  },
  {
    "tenantId": "{{rdmTenant}}",
    "type": "rdm/lookupTypes/StockExchanges",
    "code": "LMAX",
    "enabled": true,
    "startDate": "0",
    "endDate": "0",
    "updatedBy": "proactive_monitoring_service",
    "version": "1",
    "sourceMappings": [
      {
        "source": "Reltio",
        "values": [
          {
            "code": "LMAX",
            "value": "LMAX",
            "canonicalValue": "true",
            "downStreamDefaultValue": true,
            "enabled": true
          }
        ]
      }
    ]
  },
  {
    "tenantId": "{{rdmTenant}}",
    "type": "rdm/lookupTypes/StockExchanges",
    "code": "LMEC",
    "enabled": true,
    "startDate": "0",
    "endDate": "0",
    "updatedBy": "proactive_monitoring_service",
    "version": "1",
    "sourceMappings": [
      {
        "source": "Reltio",
        "values": [
          {
            "code": "LMEC",
            "value": "LME CLEAR",
            "canonicalValue": "true",
            "downStreamDefaultValue": true,
            "enabled": true
          }
        ]
      }
    ]
  },
  {
    "tenantId": "{{rdmTenant}}",
    "type": "rdm/lookupTypes/StockExchanges",
    "code": "LMNR",
    "enabled": true,
    "startDate": "0",
    "endDate": "0",
    "updatedBy": "proactive_monitoring_service",
    "version": "1",
    "sourceMappings": [
      {
        "source": "Reltio",
        "values": [
          {
            "code": "LMNR",
            "value": "LUMINOR BANK AS",
            "canonicalValue": "true",
            "downStreamDefaultValue": true,
            "enabled": true
          }
        ]
      }
    ]
  },
  {
    "tenantId": "{{rdmTenant}}",
    "type": "rdm/lookupTypes/StockExchanges",
    "code": "LMNX",
    "enabled": true,
    "startDate": "0",
    "endDate": "0",
    "updatedBy": "proactive_monitoring_service",
    "version": "1",
    "sourceMappings": [
      {
        "source": "Reltio",
        "values": [
          {
            "code": "LMNX",
            "value": "LUMINEX TRADING & ANALYTICS LLC - ATS",
            "canonicalValue": "true",
            "downStreamDefaultValue": true,
            "enabled": true
          }
        ]
      }
    ]
  },
  {
    "tenantId": "{{rdmTenant}}",
    "type": "rdm/lookupTypes/StockExchanges",
    "code": "LMTS",
    "enabled": true,
    "startDate": "0",
    "endDate": "0",
    "updatedBy": "proactive_monitoring_service",
    "version": "1",
    "sourceMappings": [
      {
        "source": "Reltio",
        "values": [
          {
            "code": "LMTS",
            "value": "EUROGLOBALMTS",
            "canonicalValue": "true",
            "downStreamDefaultValue": true,
            "enabled": true
          }
        ]
      }
    ]
  },
  {
    "tenantId": "{{rdmTenant}}",
    "type": "rdm/lookupTypes/StockExchanges",
    "code": "LNEQ",
    "enabled": true,
    "startDate": "0",
    "endDate": "0",
    "updatedBy": "proactive_monitoring_service",
    "version": "1",
    "sourceMappings": [
      {
        "source": "Reltio",
        "values": [
          {
            "code": "LNEQ",
            "value": "TP ICAP EU - MTF - LIQUIDNET EU EQUITY",
            "canonicalValue": "true",
            "downStreamDefaultValue": true,
            "enabled": true
          }
        ]
      }
    ]
  },
  {
    "tenantId": "{{rdmTenant}}",
    "type": "rdm/lookupTypes/StockExchanges",
    "code": "LNFI",
    "enabled": true,
    "startDate": "0",
    "endDate": "0",
    "updatedBy": "proactive_monitoring_service",
    "version": "1",
    "sourceMappings": [
      {
        "source": "Reltio",
        "values": [
          {
            "code": "LNFI",
            "value": "TP ICAP EU - MTF - LIQUIDNET EU FIXED INCOME",
            "canonicalValue": "true",
            "downStreamDefaultValue": true,
            "enabled": true
          }
        ]
      }
    ]
  },
  {
    "tenantId": "{{rdmTenant}}",
    "type": "rdm/lookupTypes/StockExchanges",
    "code": "LOTC",
    "enabled": true,
    "startDate": "0",
    "endDate": "0",
    "updatedBy": "proactive_monitoring_service",
    "version": "1",
    "sourceMappings": [
      {
        "source": "Reltio",
        "values": [
          {
            "code": "LOTC",
            "value": "OTC MARKET",
            "canonicalValue": "true",
            "downStreamDefaultValue": true,
            "enabled": true
          }
        ]
      }
    ]
  },
  {
    "tenantId": "{{rdmTenant}}",
    "type": "rdm/lookupTypes/StockExchanges",
    "code": "LOUI",
    "enabled": true,
    "startDate": "0",
    "endDate": "0",
    "updatedBy": "proactive_monitoring_service",
    "version": "1",
    "sourceMappings": [
      {
        "source": "Reltio",
        "values": [
          {
            "code": "LOUI",
            "value": "LOUIS CAPITAL MARKETS UK LLP",
            "canonicalValue": "true",
            "downStreamDefaultValue": true,
            "enabled": true
          }
        ]
      }
    ]
  },
  {
    "tenantId": "{{rdmTenant}}",
    "type": "rdm/lookupTypes/StockExchanges",
    "code": "LOYD",
    "enabled": true,
    "startDate": "0",
    "endDate": "0",
    "updatedBy": "proactive_monitoring_service",
    "version": "1",
    "sourceMappings": [
      {
        "source": "Reltio",
        "values": [
          {
            "code": "LOYD",
            "value": "LLOYDS BANK",
            "canonicalValue": "true",
            "downStreamDefaultValue": true,
            "enabled": true
          }
        ]
      }
    ]
  },
  {
    "tenantId": "{{rdmTenant}}",
    "type": "rdm/lookupTypes/StockExchanges",
    "code": "LPPM",
    "enabled": true,
    "startDate": "0",
    "endDate": "0",
    "updatedBy": "proactive_monitoring_service",
    "version": "1",
    "sourceMappings": [
      {
        "source": "Reltio",
        "values": [
          {
            "code": "LPPM",
            "value": "LONDON PLATINUM AND PALLADIUM MARKET",
            "canonicalValue": "true",
            "downStreamDefaultValue": true,
            "enabled": true
          }
        ]
      }
    ]
  },
  {
    "tenantId": "{{rdmTenant}}",
    "type": "rdm/lookupTypes/StockExchanges",
    "code": "LPSF",
    "enabled": true,
    "startDate": "0",
    "endDate": "0",
    "updatedBy": "proactive_monitoring_service",
    "version": "1",
    "sourceMappings": [
      {
        "source": "Reltio",
        "values": [
          {
            "code": "LPSF",
            "value": "LPSFX LLC",
            "canonicalValue": "true",
            "downStreamDefaultValue": true,
            "enabled": true
          }
        ]
      }
    ]
  },
  {
    "tenantId": "{{rdmTenant}}",
    "type": "rdm/lookupTypes/StockExchanges",
    "code": "LQED",
    "enabled": true,
    "startDate": "0",
    "endDate": "0",
    "updatedBy": "proactive_monitoring_service",
    "version": "1",
    "sourceMappings": [
      {
        "source": "Reltio",
        "values": [
          {
            "code": "LQED",
            "value": "LIQUIDITYEDGE",
            "canonicalValue": "true",
            "downStreamDefaultValue": true,
            "enabled": true
          }
        ]
      }
    ]
  },
  {
    "tenantId": "{{rdmTenant}}",
    "type": "rdm/lookupTypes/StockExchanges",
    "code": "LQFI",
    "enabled": true,
    "startDate": "0",
    "endDate": "0",
    "updatedBy": "proactive_monitoring_service",
    "version": "1",
    "sourceMappings": [
      {
        "source": "Reltio",
        "values": [
          {
            "code": "LQFI",
            "value": "CITI LIQUIFI",
            "canonicalValue": "true",
            "downStreamDefaultValue": true,
            "enabled": true
          }
        ]
      }
    ]
  },
  {
    "tenantId": "{{rdmTenant}}",
    "type": "rdm/lookupTypes/StockExchanges",
    "code": "LSSI",
    "enabled": true,
    "startDate": "0",
    "endDate": "0",
    "updatedBy": "proactive_monitoring_service",
    "version": "1",
    "sourceMappings": [
      {
        "source": "Reltio",
        "values": [
          {
            "code": "LSSI",
            "value": "LANG AND SCHWARZ TRADE CENTER",
            "canonicalValue": "true",
            "downStreamDefaultValue": true,
            "enabled": true
          }
        ]
      }
    ]
  },
  {
    "tenantId": "{{rdmTenant}}",
    "type": "rdm/lookupTypes/StockExchanges",
    "code": "LTAA",
    "enabled": true,
    "startDate": "0",
    "endDate": "0",
    "updatedBy": "proactive_monitoring_service",
    "version": "1",
    "sourceMappings": [
      {
        "source": "Reltio",
        "values": [
          {
            "code": "LTAA",
            "value": "LUMINEX TRADING & ANALYTICS LLC",
            "canonicalValue": "true",
            "downStreamDefaultValue": true,
            "enabled": true
          }
        ]
      }
    ]
  },
  {
    "tenantId": "{{rdmTenant}}",
    "type": "rdm/lookupTypes/StockExchanges",
    "code": "LTSE",
    "enabled": true,
    "startDate": "0",
    "endDate": "0",
    "updatedBy": "proactive_monitoring_service",
    "version": "1",
    "sourceMappings": [
      {
        "source": "Reltio",
        "values": [
          {
            "code": "LTSE",
            "value": "LONG-TERM STOCK EXCHANGE, INC.",
            "canonicalValue": "true",
            "downStreamDefaultValue": true,
            "enabled": true
          }
        ]
      }
    ]
  },
  {
    "tenantId": "{{rdmTenant}}",
    "type": "rdm/lookupTypes/StockExchanges",
    "code": "LXJP",
    "enabled": true,
    "startDate": "0",
    "endDate": "0",
    "updatedBy": "proactive_monitoring_service",
    "version": "1",
    "sourceMappings": [
      {
        "source": "Reltio",
        "values": [
          {
            "code": "LXJP",
            "value": "BARCLAYS LX JAPAN",
            "canonicalValue": "true",
            "downStreamDefaultValue": true,
            "enabled": true
          }
        ]
      }
    ]
  },
  {
    "tenantId": "{{rdmTenant}}",
    "type": "rdm/lookupTypes/StockExchanges",
    "code": "LYNX",
    "enabled": true,
    "startDate": "0",
    "endDate": "0",
    "updatedBy": "proactive_monitoring_service",
    "version": "1",
    "sourceMappings": [
      {
        "source": "Reltio",
        "values": [
          {
            "code": "LYNX",
            "value": "LYNX ATS",
            "canonicalValue": "true",
            "downStreamDefaultValue": true,
            "enabled": true
          }
        ]
      }
    ]
  },
  {
    "tenantId": "{{rdmTenant}}",
    "type": "rdm/lookupTypes/StockExchanges",
    "code": "MABX",
    "enabled": true,
    "startDate": "0",
    "endDate": "0",
    "updatedBy": "proactive_monitoring_service",
    "version": "1",
    "sourceMappings": [
      {
        "source": "Reltio",
        "values": [
          {
            "code": "MABX",
            "value": "BME MTF EQUITY (IIC AND ECR SEGMENTS)",
            "canonicalValue": "true",
            "downStreamDefaultValue": true,
            "enabled": true
          }
        ]
      }
    ]
  },
  {
    "tenantId": "{{rdmTenant}}",
    "type": "rdm/lookupTypes/StockExchanges",
    "code": "MACB",
    "enabled": true,
    "startDate": "0",
    "endDate": "0",
    "updatedBy": "proactive_monitoring_service",
    "version": "1",
    "sourceMappings": [
      {
        "source": "Reltio",
        "values": [
          {
            "code": "MACB",
            "value": "MACQUARIE AUSTRALIA BLOCK CROSSING",
            "canonicalValue": "true",
            "downStreamDefaultValue": true,
            "enabled": true
          }
        ]
      }
    ]
  },
  {
    "tenantId": "{{rdmTenant}}",
    "type": "rdm/lookupTypes/StockExchanges",
    "code": "MACX",
    "enabled": true,
    "startDate": "0",
    "endDate": "0",
    "updatedBy": "proactive_monitoring_service",
    "version": "1",
    "sourceMappings": [
      {
        "source": "Reltio",
        "values": [
          {
            "code": "MACX",
            "value": "MERCATO ALTERNATIVO DEL CAPITALE",
            "canonicalValue": "true",
            "downStreamDefaultValue": true,
            "enabled": true
          }
        ]
      }
    ]
  },
  {
    "tenantId": "{{rdmTenant}}",
    "type": "rdm/lookupTypes/StockExchanges",
    "code": "MAEL",
    "enabled": true,
    "startDate": "0",
    "endDate": "0",
    "updatedBy": "proactive_monitoring_service",
    "version": "1",
    "sourceMappings": [
      {
        "source": "Reltio",
        "values": [
          {
            "code": "MAEL",
            "value": "MARKETAXESS EUROPE LIMITED",
            "canonicalValue": "true",
            "downStreamDefaultValue": true,
            "enabled": true
          }
        ]
      }
    ]
  },
  {
    "tenantId": "{{rdmTenant}}",
    "type": "rdm/lookupTypes/StockExchanges",
    "code": "MAGM",
    "enabled": true,
    "startDate": "0",
    "endDate": "0",
    "updatedBy": "proactive_monitoring_service",
    "version": "1",
    "sourceMappings": [
      {
        "source": "Reltio",
        "values": [
          {
            "code": "MAGM",
            "value": "MAGMA ATS",
            "canonicalValue": "true",
            "downStreamDefaultValue": true,
            "enabled": true
          }
        ]
      }
    ]
  },
  {
    "tenantId": "{{rdmTenant}}",
    "type": "rdm/lookupTypes/StockExchanges",
    "code": "MAKX",
    "enabled": true,
    "startDate": "0",
    "endDate": "0",
    "updatedBy": "proactive_monitoring_service",
    "version": "1",
    "sourceMappings": [
      {
        "source": "Reltio",
        "values": [
          {
            "code": "MAKX",
            "value": "MAKOR SECURITIES LONDON LTD",
            "canonicalValue": "true",
            "downStreamDefaultValue": true,
            "enabled": true
          }
        ]
      }
    ]
  },
  {
    "tenantId": "{{rdmTenant}}",
    "type": "rdm/lookupTypes/StockExchanges",
    "code": "MALM",
    "enabled": true,
    "startDate": "0",
    "endDate": "0",
    "updatedBy": "proactive_monitoring_service",
    "version": "1",
    "sourceMappings": [
      {
        "source": "Reltio",
        "values": [
          {
            "code": "MALM",
            "value": "MARKETAXESS SINGAPORE PTE LIMITED - LIVE MARKETS",
            "canonicalValue": "true",
            "downStreamDefaultValue": true,
            "enabled": true
          }
        ]
      }
    ]
  },
  {
    "tenantId": "{{rdmTenant}}",
    "type": "rdm/lookupTypes/StockExchanges",
    "code": "MALX",
    "enabled": true,
    "startDate": "0",
    "endDate": "0",
    "updatedBy": "proactive_monitoring_service",
    "version": "1",
    "sourceMappings": [
      {
        "source": "Reltio",
        "values": [
          {
            "code": "MALX",
            "value": "MALDIVES STOCK EXCHANGE",
            "canonicalValue": "true",
            "downStreamDefaultValue": true,
            "enabled": true
          }
        ]
      }
    ]
  },
  {
    "tenantId": "{{rdmTenant}}",
    "type": "rdm/lookupTypes/StockExchanges",
    "code": "MANL",
    "enabled": true,
    "startDate": "0",
    "endDate": "0",
    "updatedBy": "proactive_monitoring_service",
    "version": "1",
    "sourceMappings": [
      {
        "source": "Reltio",
        "values": [
          {
            "code": "MANL",
            "value": "MARKETAXESS NL B.V.",
            "canonicalValue": "true",
            "downStreamDefaultValue": true,
            "enabled": true
          }
        ]
      }
    ]
  },
  {
    "tenantId": "{{rdmTenant}}",
    "type": "rdm/lookupTypes/StockExchanges",
    "code": "MAQE",
    "enabled": true,
    "startDate": "0",
    "endDate": "0",
    "updatedBy": "proactive_monitoring_service",
    "version": "1",
    "sourceMappings": [
      {
        "source": "Reltio",
        "values": [
          {
            "code": "MAQE",
            "value": "MACQUARIE BANK EUROPE DESIGNATED ACTIVITY COMPANY",
            "canonicalValue": "true",
            "downStreamDefaultValue": true,
            "enabled": true
          }
        ]
      }
    ]
  },
  {
    "tenantId": "{{rdmTenant}}",
    "type": "rdm/lookupTypes/StockExchanges",
    "code": "MAQH",
    "enabled": true,
    "startDate": "0",
    "endDate": "0",
    "updatedBy": "proactive_monitoring_service",
    "version": "1",
    "sourceMappings": [
      {
        "source": "Reltio",
        "values": [
          {
            "code": "MAQH",
            "value": "MACQUARIE INTERNAL MARKETS (HONG KONG)",
            "canonicalValue": "true",
            "downStreamDefaultValue": true,
            "enabled": true
          }
        ]
      }
    ]
  },
  {
    "tenantId": "{{rdmTenant}}",
    "type": "rdm/lookupTypes/StockExchanges",
    "code": "MAQI",
    "enabled": true,
    "startDate": "0",
    "endDate": "0",
    "updatedBy": "proactive_monitoring_service",
    "version": "1",
    "sourceMappings": [
      {
        "source": "Reltio",
        "values": [
          {
            "code": "MAQI",
            "value": "MACQUARIE BANK INTERNATIONAL LIMITED",
            "canonicalValue": "true",
            "downStreamDefaultValue": true,
            "enabled": true
          }
        ]
      }
    ]
  },
  {
    "tenantId": "{{rdmTenant}}",
    "type": "rdm/lookupTypes/StockExchanges",
    "code": "MAQJ",
    "enabled": true,
    "startDate": "0",
    "endDate": "0",
    "updatedBy": "proactive_monitoring_service",
    "version": "1",
    "sourceMappings": [
      {
        "source": "Reltio",
        "values": [
          {
            "code": "MAQJ",
            "value": "MACQUARIE INTERNAL MARKETS (JAPAN)",
            "canonicalValue": "true",
            "downStreamDefaultValue": true,
            "enabled": true
          }
        ]
      }
    ]
  },
  {
    "tenantId": "{{rdmTenant}}",
    "type": "rdm/lookupTypes/StockExchanges",
    "code": "MAQL",
    "enabled": true,
    "startDate": "0",
    "endDate": "0",
    "updatedBy": "proactive_monitoring_service",
    "version": "1",
    "sourceMappings": [
      {
        "source": "Reltio",
        "values": [
          {
            "code": "MAQL",
            "value": "MACQUARIE CAPITAL EUROPE LIMITED",
            "canonicalValue": "true",
            "downStreamDefaultValue": true,
            "enabled": true
          }
        ]
      }
    ]
  },
  {
    "tenantId": "{{rdmTenant}}",
    "type": "rdm/lookupTypes/StockExchanges",
    "code": "MAQU",
    "enabled": true,
    "startDate": "0",
    "endDate": "0",
    "updatedBy": "proactive_monitoring_service",
    "version": "1",
    "sourceMappings": [
      {
        "source": "Reltio",
        "values": [
          {
            "code": "MAQU",
            "value": "MACQUARIE BANK LIMITED, LONDON BRANCH",
            "canonicalValue": "true",
            "downStreamDefaultValue": true,
            "enabled": true
          }
        ]
      }
    ]
  },
  {
    "tenantId": "{{rdmTenant}}",
    "type": "rdm/lookupTypes/StockExchanges",
    "code": "MAQX",
    "enabled": true,
    "startDate": "0",
    "endDate": "0",
    "updatedBy": "proactive_monitoring_service",
    "version": "1",
    "sourceMappings": [
      {
        "source": "Reltio",
        "values": [
          {
            "code": "MAQX",
            "value": "MACQUARIE INTERNAL MARKETS (AUSTRALIA)",
            "canonicalValue": "true",
            "downStreamDefaultValue": true,
            "enabled": true
          }
        ]
      }
    ]
  },
  {
    "tenantId": "{{rdmTenant}}",
    "type": "rdm/lookupTypes/StockExchanges",
    "code": "MARF",
    "enabled": true,
    "startDate": "0",
    "endDate": "0",
    "updatedBy": "proactive_monitoring_service",
    "version": "1",
    "sourceMappings": [
      {
        "source": "Reltio",
        "values": [
          {
            "code": "MARF",
            "value": "MERCADO ALTERNATIVO DE RENTA FIJA",
            "canonicalValue": "true",
            "downStreamDefaultValue": true,
            "enabled": true
          }
        ]
      }
    ]
  },
  {
    "tenantId": "{{rdmTenant}}",
    "type": "rdm/lookupTypes/StockExchanges",
    "code": "MASG",
    "enabled": true,
    "startDate": "0",
    "endDate": "0",
    "updatedBy": "proactive_monitoring_service",
    "version": "1",
    "sourceMappings": [
      {
        "source": "Reltio",
        "values": [
          {
            "code": "MASG",
            "value": "MARKETAXESS SINGAPORE PTE LIMITED",
            "canonicalValue": "true",
            "downStreamDefaultValue": true,
            "enabled": true
          }
        ]
      }
    ]
  },
  {
    "tenantId": "{{rdmTenant}}",
    "type": "rdm/lookupTypes/StockExchanges",
    "code": "MATN",
    "enabled": true,
    "startDate": "0",
    "endDate": "0",
    "updatedBy": "proactive_monitoring_service",
    "version": "1",
    "sourceMappings": [
      {
        "source": "Reltio",
        "values": [
          {
            "code": "MATN",
            "value": "MATCH NOW",
            "canonicalValue": "true",
            "downStreamDefaultValue": true,
            "enabled": true
          }
        ]
      }
    ]
  },
  {
    "tenantId": "{{rdmTenant}}",
    "type": "rdm/lookupTypes/StockExchanges",
    "code": "MATX",
    "enabled": true,
    "startDate": "0",
    "endDate": "0",
    "updatedBy": "proactive_monitoring_service",
    "version": "1",
    "sourceMappings": [
      {
        "source": "Reltio",
        "values": [
          {
            "code": "MATX",
            "value": "MATRIX LIMITED",
            "canonicalValue": "true",
            "downStreamDefaultValue": true,
            "enabled": true
          }
        ]
      }
    ]
  },
  {
    "tenantId": "{{rdmTenant}}",
    "type": "rdm/lookupTypes/StockExchanges",
    "code": "MAXD",
    "enabled": true,
    "startDate": "0",
    "endDate": "0",
    "updatedBy": "proactive_monitoring_service",
    "version": "1",
    "sourceMappings": [
      {
        "source": "Reltio",
        "values": [
          {
            "code": "MAXD",
            "value": "MAX MARKETS LIMITED",
            "canonicalValue": "true",
            "downStreamDefaultValue": true,
            "enabled": true
          }
        ]
      }
    ]
  },
  {
    "tenantId": "{{rdmTenant}}",
    "type": "rdm/lookupTypes/StockExchanges",
    "code": "MBCP",
    "enabled": true,
    "startDate": "0",
    "endDate": "0",
    "updatedBy": "proactive_monitoring_service",
    "version": "1",
    "sourceMappings": [
      {
        "source": "Reltio",
        "values": [
          {
            "code": "MBCP",
            "value": "MILLENNIUM BCP",
            "canonicalValue": "true",
            "downStreamDefaultValue": true,
            "enabled": true
          }
        ]
      }
    ]
  },
  {
    "tenantId": "{{rdmTenant}}",
    "type": "rdm/lookupTypes/StockExchanges",
    "code": "MBPL",
    "enabled": true,
    "startDate": "0",
    "endDate": "0",
    "updatedBy": "proactive_monitoring_service",
    "version": "1",
    "sourceMappings": [
      {
        "source": "Reltio",
        "values": [
          {
            "code": "MBPL",
            "value": "MBANK S.A.",
            "canonicalValue": "true",
            "downStreamDefaultValue": true,
            "enabled": true
          }
        ]
      }
    ]
  },
  {
    "tenantId": "{{rdmTenant}}",
    "type": "rdm/lookupTypes/StockExchanges",
    "code": "MBSI",
    "enabled": true,
    "startDate": "0",
    "endDate": "0",
    "updatedBy": "proactive_monitoring_service",
    "version": "1",
    "sourceMappings": [
      {
        "source": "Reltio",
        "values": [
          {
            "code": "MBSI",
            "value": "MORGAN STANLEY BANK INTERNATIONAL LIMITED - SYSTEMATIC INTERNALISER",
            "canonicalValue": "true",
            "downStreamDefaultValue": true,
            "enabled": true
          }
        ]
      }
    ]
  },
  {
    "tenantId": "{{rdmTenant}}",
    "type": "rdm/lookupTypes/StockExchanges",
    "code": "MBUL",
    "enabled": true,
    "startDate": "0",
    "endDate": "0",
    "updatedBy": "proactive_monitoring_service",
    "version": "1",
    "sourceMappings": [
      {
        "source": "Reltio",
        "values": [
          {
            "code": "MBUL",
            "value": "MTF SOFIA",
            "canonicalValue": "true",
            "downStreamDefaultValue": true,
            "enabled": true
          }
        ]
      }
    ]
  },
  {
    "tenantId": "{{rdmTenant}}",
    "type": "rdm/lookupTypes/StockExchanges",
    "code": "MCAD",
    "enabled": true,
    "startDate": "0",
    "endDate": "0",
    "updatedBy": "proactive_monitoring_service",
    "version": "1",
    "sourceMappings": [
      {
        "source": "Reltio",
        "values": [
          {
            "code": "MCAD",
            "value": "MTS CASH DOMESTIC - MTF",
            "canonicalValue": "true",
            "downStreamDefaultValue": true,
            "enabled": true
          }
        ]
      }
    ]
  },
  {
    "tenantId": "{{rdmTenant}}",
    "type": "rdm/lookupTypes/StockExchanges",
    "code": "MCID",
    "enabled": true,
    "startDate": "0",
    "endDate": "0",
    "updatedBy": "proactive_monitoring_service",
    "version": "1",
    "sourceMappings": [
      {
        "source": "Reltio",
        "values": [
          {
            "code": "MCID",
            "value": "MACQUARIE CAPITAL (IRELAND)",
            "canonicalValue": "true",
            "downStreamDefaultValue": true,
            "enabled": true
          }
        ]
      }
    ]
  },
  {
    "tenantId": "{{rdmTenant}}",
    "type": "rdm/lookupTypes/StockExchanges",
    "code": "MCRY",
    "enabled": true,
    "startDate": "0",
    "endDate": "0",
    "updatedBy": "proactive_monitoring_service",
    "version": "1",
    "sourceMappings": [
      {
        "source": "Reltio",
        "values": [
          {
            "code": "MCRY",
            "value": "ISE MERCURY, LLC",
            "canonicalValue": "true",
            "downStreamDefaultValue": true,
            "enabled": true
          }
        ]
      }
    ]
  },
  {
    "tenantId": "{{rdmTenant}}",
    "type": "rdm/lookupTypes/StockExchanges",
    "code": "MCSE",
    "enabled": true,
    "startDate": "0",
    "endDate": "0",
    "updatedBy": "proactive_monitoring_service",
    "version": "1",
    "sourceMappings": [
      {
        "source": "Reltio",
        "values": [
          {
            "code": "MCSE",
            "value": "NASDAQ COPENHAGEN A/S - AUCTION ON DEMAND",
            "canonicalValue": "true",
            "downStreamDefaultValue": true,
            "enabled": true
          }
        ]
      }
    ]
  },
  {
    "tenantId": "{{rdmTenant}}",
    "type": "rdm/lookupTypes/StockExchanges",
    "code": "MCUR",
    "enabled": true,
    "startDate": "0",
    "endDate": "0",
    "updatedBy": "proactive_monitoring_service",
    "version": "1",
    "sourceMappings": [
      {
        "source": "Reltio",
        "values": [
          {
            "code": "MCUR",
            "value": "CURRENEX MTF",
            "canonicalValue": "true",
            "downStreamDefaultValue": true,
            "enabled": true
          }
        ]
      }
    ]
  },
  {
    "tenantId": "{{rdmTenant}}",
    "type": "rdm/lookupTypes/StockExchanges",
    "code": "MCXR",
    "enabled": true,
    "startDate": "0",
    "endDate": "0",
    "updatedBy": "proactive_monitoring_service",
    "version": "1",
    "sourceMappings": [
      {
        "source": "Reltio",
        "values": [
          {
            "code": "MCXR",
            "value": "CURRENEX MTF - RFQ",
            "canonicalValue": "true",
            "downStreamDefaultValue": true,
            "enabled": true
          }
        ]
      }
    ]
  },
  {
    "tenantId": "{{rdmTenant}}",
    "type": "rdm/lookupTypes/StockExchanges",
    "code": "MCXS",
    "enabled": true,
    "startDate": "0",
    "endDate": "0",
    "updatedBy": "proactive_monitoring_service",
    "version": "1",
    "sourceMappings": [
      {
        "source": "Reltio",
        "values": [
          {
            "code": "MCXS",
            "value": "CURRENEX MTF - STREAMING",
            "canonicalValue": "true",
            "downStreamDefaultValue": true,
            "enabled": true
          }
        ]
      }
    ]
  },
  {
    "tenantId": "{{rdmTenant}}",
    "type": "rdm/lookupTypes/StockExchanges",
    "code": "MCXX",
    "enabled": true,
    "startDate": "0",
    "endDate": "0",
    "updatedBy": "proactive_monitoring_service",
    "version": "1",
    "sourceMappings": [
      {
        "source": "Reltio",
        "values": [
          {
            "code": "MCXX",
            "value": "METROPOLITAN STOCK EXCHANGE OF INDIA LIMITED",
            "canonicalValue": "true",
            "downStreamDefaultValue": true,
            "enabled": true
          }
        ]
      }
    ]
  },
  {
    "tenantId": "{{rdmTenant}}",
    "type": "rdm/lookupTypes/StockExchanges",
    "code": "MCZK",
    "enabled": true,
    "startDate": "0",
    "endDate": "0",
    "updatedBy": "proactive_monitoring_service",
    "version": "1",
    "sourceMappings": [
      {
        "source": "Reltio",
        "values": [
          {
            "code": "MCZK",
            "value": "MTS CZECH REPUBLIC",
            "canonicalValue": "true",
            "downStreamDefaultValue": true,
            "enabled": true
          }
        ]
      }
    ]
  },
  {
    "tenantId": "{{rdmTenant}}",
    "type": "rdm/lookupTypes/StockExchanges",
    "code": "MDIP",
    "enabled": true,
    "startDate": "0",
    "endDate": "0",
    "updatedBy": "proactive_monitoring_service",
    "version": "1",
    "sourceMappings": [
      {
        "source": "Reltio",
        "values": [
          {
            "code": "MDIP",
            "value": "MEDIP  (MTS PORTUGAL SGMR, SA)",
            "canonicalValue": "true",
            "downStreamDefaultValue": true,
            "enabled": true
          }
        ]
      }
    ]
  },
  {
    "tenantId": "{{rdmTenant}}",
    "type": "rdm/lookupTypes/StockExchanges",
    "code": "MDRV",
    "enabled": true,
    "startDate": "0",
    "endDate": "0",
    "updatedBy": "proactive_monitoring_service",
    "version": "1",
    "sourceMappings": [
      {
        "source": "Reltio",
        "values": [
          {
            "code": "MDRV",
            "value": "MIBGAS - DERIVATIVES",
            "canonicalValue": "true",
            "downStreamDefaultValue": true,
            "enabled": true
          }
        ]
      }
    ]
  },
  {
    "tenantId": "{{rdmTenant}}",
    "type": "rdm/lookupTypes/StockExchanges",
    "code": "MEAU",
    "enabled": true,
    "startDate": "0",
    "endDate": "0",
    "updatedBy": "proactive_monitoring_service",
    "version": "1",
    "sourceMappings": [
      {
        "source": "Reltio",
        "values": [
          {
            "code": "MEAU",
            "value": "MACQUARIE EXECUTION (AU)",
            "canonicalValue": "true",
            "downStreamDefaultValue": true,
            "enabled": true
          }
        ]
      }
    ]
  },
  {
    "tenantId": "{{rdmTenant}}",
    "type": "rdm/lookupTypes/StockExchanges",
    "code": "MEHK",
    "enabled": true,
    "startDate": "0",
    "endDate": "0",
    "updatedBy": "proactive_monitoring_service",
    "version": "1",
    "sourceMappings": [
      {
        "source": "Reltio",
        "values": [
          {
            "code": "MEHK",
            "value": "MACQUARIE EXECUTION (HK)",
            "canonicalValue": "true",
            "downStreamDefaultValue": true,
            "enabled": true
          }
        ]
      }
    ]
  },
  {
    "tenantId": "{{rdmTenant}}",
    "type": "rdm/lookupTypes/StockExchanges",
    "code": "MELO",
    "enabled": true,
    "startDate": "0",
    "endDate": "0",
    "updatedBy": "proactive_monitoring_service",
    "version": "1",
    "sourceMappings": [
      {
        "source": "Reltio",
        "values": [
          {
            "code": "MELO",
            "value": "NASDAQ MIDPOINT-ELO (M-ELO)",
            "canonicalValue": "true",
            "downStreamDefaultValue": true,
            "enabled": true
          }
        ]
      }
    ]
  }
]